[
null,
{"id":1,"expanded":true,"name":"Outside","order":2,"parentId":6,"scrollX":1081.3333333333333,"scrollY":615.3333333333334,"quick":false},
{"id":2,"expanded":true,"name":"boulderPass","order":4,"parentId":5,"scrollX":1216,"scrollY":624,"quick":false},
{"id":3,"expanded":true,"name":"insideBoulderPass","order":6,"parentId":4,"scrollX":1216.5,"scrollY":680.25,"quick":false},
{"id":4,"expanded":true,"name":"TheFPass","order":5,"parentId":2,"scrollX":4325.333333333333,"scrollY":2461.3333333333335,"quick":false},
{"id":5,"expanded":true,"name":"InsideHouse","order":3,"parentId":1,"scrollX":832,"scrollY":624,"quick":false},
{"id":6,"expanded":true,"name":"OutsideM","order":1,"parentId":0,"scrollX":1081.3333333333333,"scrollY":680.6666666666666,"quick":false},
{"id":7,"expanded":false,"name":"InsideStore","order":10,"parentId":6,"scrollX":884.7272727272727,"scrollY":494.72727272727275,"quick":false},
{"id":8,"expanded":false,"name":"Dark","order":7,"parentId":3,"scrollX":884.7272727272727,"scrollY":494.72727272727275,"quick":false},
{"id":9,"expanded":true,"name":"OutsideSchool","order":8,"parentId":4,"scrollX":1216.5,"scrollY":680.25,"quick":false},
{"id":10,"expanded":false,"name":"InsideSchool","order":9,"parentId":9,"scrollX":1216.5,"scrollY":680.25,"quick":false}
]